LICENSE
MANIFEST.in
README.rst
setup.py
cmsplugin_iframe/__init__.py
cmsplugin_iframe/cms_plugins.py
cmsplugin_iframe/forms.py
cmsplugin_iframe/models.py
cmsplugin_iframe.egg-info/PKG-INFO
cmsplugin_iframe.egg-info/SOURCES.txt
cmsplugin_iframe.egg-info/dependency_links.txt
cmsplugin_iframe.egg-info/not-zip-safe
cmsplugin_iframe.egg-info/requires.txt
cmsplugin_iframe.egg-info/top_level.txt
cmsplugin_iframe/locale/ar/LC_MESSAGES/django.mo
cmsplugin_iframe/locale/ar/LC_MESSAGES/django.po
cmsplugin_iframe/locale/en/LC_MESSAGES/django.mo
cmsplugin_iframe/locale/en/LC_MESSAGES/django.po
cmsplugin_iframe/locale/ru/LC_MESSAGES/django.mo
cmsplugin_iframe/locale/ru/LC_MESSAGES/django.po
cmsplugin_iframe/migrations/0001_initial.py
cmsplugin_iframe/migrations/__init__.py
cmsplugin_iframe/south_migrations/0001_initial.py
cmsplugin_iframe/south_migrations/__init__.py
cmsplugin_iframe/templates/cms/plugins/iframe.html