Metadata-Version: 1.1
Name: cmsplugin-iframe
Version: 0.1.3
Summary: Django CMS page iframe plugin
Home-page: https://github.com/satyrius/cmsplugin-iframe
Author: Anton Egorov
Author-email: anton.egoroff@gmail.com
License: MIT
Platform: OS Independent
Classifier: Development Status :: 4 - Beta
Classifier: Environment :: Web Environment
Classifier: Framework :: Django
Classifier: Framework :: Django :: 1.5
Classifier: Framework :: Django :: 1.6
Classifier: Framework :: Django :: 1.7
Classifier: Framework :: Django :: 1.8
Classifier: Intended Audience :: Developers
Classifier: License :: OSI Approved :: MIT License
Classifier: Operating System :: OS Independent
Classifier: Programming Language :: Python
Classifier: Topic :: Communications
Classifier: Topic :: Internet :: WWW/HTTP :: Dynamic Content
Classifier: Topic :: Internet :: WWW/HTTP :: Dynamic Content :: Message Boards
Classifier: Topic :: Internet :: WWW/HTTP :: Site Management
Classifier: Programming Language :: Python :: 2
Classifier: Programming Language :: Python :: 2.7
Classifier: Programming Language :: Python :: 3
Classifier: Programming Language :: Python :: 3.4
Classifier: Programming Language :: Python :: 3.5
